MVCactus-0.0.5.dist-info/RECORD
MVCactus-0.0.5.dist-info/metadata.json
MVCactus-0.0.5.dist-info/WHEEL
MVCactus-0.0.5.dist-info/DESCRIPTION.rst
MVCactus-0.0.5.dist-info/top_level.txt
MVCactus-0.0.5.dist-info/METADATA
MVCactus/MVCactus.py
MVCactus/__init__.py
