Metadata-Version: 2.0
Name: MVCactus
Version: 0.0.5
Summary: MVCactus is a micro-framework for building simple and efficient web applications. It leverages the standard HTTP server capabilities of Python to provide a straightforward environment for web development. MVCactus is ideal for small-scale projects, educational purposes, and rapid prototyping, offering a minimalistic approach to web server architecture with support for dynamic template rendering and static file serving.
Author: Dekel Cohen
Author-email: <dcohen52@gmail.com>
Keywords: python,web server,MVCactus,HTTP server,framework,simple web applications,web development,lightweight server,educational,template rendering,static file serving
Classifier: Development Status :: 3 - Alpha
Classifier: Intended Audience :: Developers
Classifier: Programming Language :: Python :: 3
Classifier: Operating System :: Unix
Classifier: Operating System :: MacOS :: MacOS X
Classifier: Operating System :: Microsoft :: Windows
License-File: LICENSE
